tcapy/__init__.py
tcapy/analysis/__init__.py
tcapy/analysis/dataframeholder.py
tcapy/analysis/tcaengine.py
tcapy/analysis/tcamarkettradeloader.py
tcapy/analysis/tcamarkettradeloaderimpl.py
tcapy/analysis/tcarequest.py
tcapy/analysis/tcatickerloader.py
tcapy/analysis/tcatickerloaderimpl.py
tcapy/analysis/tradeorderfilter.py
tcapy/analysis/algos/__init__.py
tcapy/analysis/algos/benchmark.py
tcapy/analysis/algos/metric.py
tcapy/analysis/algos/resultsform.py
tcapy/analysis/algos/resultssummary.py
tcapy/api/__init__.py
tcapy/api/app_api.py
tcapy/client/__init__.py
tcapy/conf/__init__.py
tcapy/conf/celery_calls.py
tcapy/conf/celeryconfig.py
tcapy/conf/common-session
tcapy/conf/common-session-noninteractive
tcapy/conf/constants.py
tcapy/conf/influxdb.conf
tcapy/conf/limits.conf
tcapy/conf/logging.conf
tcapy/conf/mongo.conf
tcapy/conf/my.cnf
tcapy/conf/redis.conf
tcapy/conf/tcapy.wsgi
tcapy/conf/tcapy_apache.conf
tcapy/conf/tcapy_apache_gunicorn.conf
tcapy/conf/tcapy_apache_gunicorn_80.conf
tcapy/conf/tcapy_nginx_gunicorn.conf
tcapy/conf/tcapy_nginx_gunicorn_docker.conf
tcapy/conf/tcapy_wsgi.py
tcapy/conf/tcapyapi.wsgi
tcapy/conf/tcapyapi_wsgi.py
tcapy/conf/tcapyboard.wsgi
tcapy/conf/tcapyboard_wsgi.py
tcapy/data/__init__.py
tcapy/data/accesscontrol.py
tcapy/data/databasepopulator.py
tcapy/data/databasesource.py
tcapy/data/datadumper.py
tcapy/data/datafactory.py
tcapy/data/datatestcreator.py
tcapy/data/volatilecache.py
tcapy/excel/__init__.py
tcapy/excel/tcapy_xl.py
tcapy/excel/tcapy_xl.xlsm
tcapy/util/__init__.py
tcapy/util/colors.py
tcapy/util/customexceptions.py
tcapy/util/deltaizeserialize.py
tcapy/util/fxconv.py
tcapy/util/loggermanager.py
tcapy/util/mediator.py
tcapy/util/singleton.py
tcapy/util/ssl_no_verify.py
tcapy/util/swim.py
tcapy/util/timeseries.py
tcapy/util/utilfunc.py
tcapy/vis/__init__.py
tcapy/vis/app.py
tcapy/vis/app_board.py
tcapy/vis/app_imports.py
tcapy/vis/candlestick.py
tcapy/vis/computationcaller.py
tcapy/vis/computationresults.py
tcapy-0.1.2.dist-info/LICENCE
tcapy-0.1.2.dist-info/METADATA
tcapy-0.1.2.dist-info/WHEEL
tcapy-0.1.2.dist-info/top_level.txt
tcapy-0.1.2.dist-info/RECORD
