Metadata-Version: 2.1
Name: tcapy
Version: 0.1.2
Summary: Tranasction cost analysis library
Home-page: https://github.com/cuemacro/tcapy
Author: Saeed Amen
Author-email: saeed@cuemacro.com
License: Apache 2.0
Keywords: pandas,TCA,transaction cost analysis
Platform: UNKNOWN
Requires-Dist: setuptools-git (==1.2)
Requires-Dist: cython
Requires-Dist: arctic (==1.79.4)
Requires-Dist: sqlalchemy (==1.3.17)
Requires-Dist: redis (==3.3.7)
Requires-Dist: pandas (==1.0.5)
Requires-Dist: numpy
Requires-Dist: scipy
Requires-Dist: statsmodels (==0.11.1)
Requires-Dist: blosc (==1.8.3)
Requires-Dist: pyarrow (==2.0.0)
Requires-Dist: pathos
Requires-Dist: multiprocess
Requires-Dist: fastparquet (==0.4.1)
Requires-Dist: flask-restplus (==0.13.0)
Requires-Dist: gunicorn (==19.9.0)
Requires-Dist: beautifulsoup4 (==4.8.0)
Requires-Dist: pdfkit (==0.6.1)
Requires-Dist: psutil (==5.6.6)
Requires-Dist: matplotlib (==3.3.1)
Requires-Dist: boto3 (==1.5.11)
Requires-Dist: pyodbc (==4.0.23)
Requires-Dist: pytest
Requires-Dist: pytest-cov
Requires-Dist: mysql-connector-python (==8.0.19)
Requires-Dist: IPython (==7.14.0)
Requires-Dist: chartpy (==0.1.8)
Requires-Dist: findatapy (==0.1.19)
Requires-Dist: dash-auth (==1.3.2)
Requires-Dist: cufflinks (==0.17.3)
Requires-Dist: plotly (==4.9.0)
Requires-Dist: kaleido
Requires-Dist: eikon (==1.1.2)
Requires-Dist: chart-studio (==1.1.0)
Requires-Dist: dash (==1.12.0)
Requires-Dist: dash-bootstrap-components (==0.10.3)
Requires-Dist: dash-html-components (==1.0.3)
Requires-Dist: dash-core-components (==1.10.0)
Requires-Dist: dash-table (==4.7.0)
Requires-Dist: jupyter-dash (==0.2.1)
Requires-Dist: dtale (==1.8.1)
Requires-Dist: qpython (==2.0.0)
Requires-Dist: influxdb (==5.2.3)
Requires-Dist: celery (==5.0.5)
Requires-Dist: pytest-tap
Requires-Dist: kombu
Requires-Dist: python-memcached (==1.59)
Requires-Dist: numba
Requires-Dist: vispy (==0.6.4)
Requires-Dist: jinja2 (==2.11.2)
Requires-Dist: jupyterlab
Requires-Dist: jupyter-contrib-nbextensions
Requires-Dist: jupyter-nbextensions-configurator
Requires-Dist: RISE
Requires-Dist: bqplot
Requires-Dist: WeasyPrint (==51)
Requires-Dist: dask (==2.14.0)
Requires-Dist: distributed (==2.14.0)
Requires-Dist: cloudpickle (==1.3.0)
Requires-Dist: python-snappy (==0.5.4)
Requires-Dist: bokeh (==2.0.1)
Requires-Dist: msgpack (==1.0.0)
Requires-Dist: pystore
Requires-Dist: fsspec (==0.3.3)
